day_date.py
day_date-0.3.8.dist-info/METADATA
day_date-0.3.8.dist-info/WHEEL
day_date-0.3.8.dist-info/entry_points.txt
day_date-0.3.8.dist-info/top_level.txt
day_date-0.3.8.dist-info/RECORD
