Metadata-Version: 2.1
Name: day_date
Version: 0.3.8
Summary: Calcule le jour de la semaine d'une date donnée
Home-page: https://github.com/bouquet-cedric/module-python
Author: Bouquet Cédric
Author-email: cedric-bouquet-7@outlook.fr
Classifier: Programming Language :: Python :: 3
Requires: colorate_console
Requires-Python: >=3.0
